{
    "content" : [
        {
            "dataId": "217904",
            "addressAmphurText": "เมือง",
            "addressMooBanText": null,
            "addressMooText": "4",
            "addressNoText": "210",
            "addressPostCode": null,
            "addressProvinceText": "สุโขทัย",
            "addressRoadText": null,
            "addressSoiText": null,
            "addressTumbonText": "บ้านสวน",
            "allegation": "พรบ.ยาเสพติดให้โทษประเภท1(ยาบ้า)จำหน่าย",
            "amountOfTimesBreakDiscipline": null,
            "citizenCardNumber": "3640100055621",
            "dataSource": "DOCDB",
            "dataSubmitDate": "2023-07-25T14:18:51.000+0000",
            "dateOfBirth": "1981-09-19",
            "decidedCaseId": "998/2550",
            "educationLevel": "มัธยมศึกษาปีที่ 3",
            "educationProvince": "สุโขทัย",
            "educationSchool": "บ้านสวนวิทยาคม",
            "firstName": "สมชาย",
            "judgement": null,
            "lastName": "ม่วงอาบ",
            "nationality": "ไทย",
            "policeCaseId": null,
            "prisonName": "เรือนจำจังหวัดสุโขทัย",
            "prisonerId": "5533700771",
            "receiveDate": "2007-09-02",
            "releaseDate": "2014-01-06",
            "religious": "พุทธ",
            "sentenceDate": null,
            "sex": "MALE",
            "undecidedCaseId": "1025/2550",
            "sexCode": "1",
            "imposeTypeCode": "1",
            "nationalityCode": "01037",
            "prisonCode": "337",
            "religiousCode": "0",
            "motherFirstName": "สนับ",
            "fatherFirstName": "ลอง",
            "motherLastName": "ม่วงอาบ",
            "fatherLastName": "ม่วงอาบ",
            "motherPrefix": "นาง",
            "fatherPrefix": "นาย",
            "courtName": "จังหวัดสุโขทัย"
        }
    ]
}